greenbutton_objects/__init__.py
greenbutton_objects/enums.py
greenbutton_objects/objects.py
greenbutton_objects/parse.py
greenbutton_objects/resources.py
greenbutton_objects/utils.py
greenbutton_objects-2024.7.11.dist-info/LICENSE
greenbutton_objects-2024.7.11.dist-info/METADATA
greenbutton_objects-2024.7.11.dist-info/NOTICE
greenbutton_objects-2024.7.11.dist-info/WHEEL
greenbutton_objects-2024.7.11.dist-info/top_level.txt
greenbutton_objects-2024.7.11.dist-info/RECORD
