Metadata-Version: 2.1
Name: greenbutton_objects
Version: 2024.7.11
Summary: Parse Green Button XML files into Python objects.
Author-email: Phil Gold <phil_g@pobox.com>, Adam Finkle <77808710+AdamFinkle@users.noreply.github.com>, Ethan Strominger <ethanstrominger2@gmail.com>
License: Copyright 2016 Phil! Gold <phil_g@pobox.com>
Project-URL: Homepage, https://github.com/codeforboston/greenbutton_objects
Keywords: feed,reader,tutorial
Classifier: License :: OSI Approved :: Apache Software License
Classifier: Programming Language :: Python
Classifier: Programming Language :: Python :: 3
Requires-Python: >=2.7
License-File: LICENSE
License-File: NOTICE
Provides-Extra: dev
Requires-Dist: black ; extra == 'dev'
Requires-Dist: bumpver ; extra == 'dev'
Requires-Dist: isort ; extra == 'dev'
Requires-Dist: mypy ; extra == 'dev'
Requires-Dist: pip-tools ; extra == 'dev'
Requires-Dist: pydocstyle ; extra == 'dev'
Requires-Dist: pytest ; extra == 'dev'
